noteblock_generator/__init__.py
noteblock_generator/__main__.py
noteblock_generator/cli/app.py
noteblock_generator/cli/args.py
noteblock_generator/cli/console.py
noteblock_generator/cli/progress_bar.py
noteblock_generator/core/blocks.py
noteblock_generator/core/chunks.py
noteblock_generator/core/coordinates.py
noteblock_generator/core/direction.py
noteblock_generator/core/generator.py
noteblock_generator/core/placement.py
noteblock_generator/core/preserve_terrain.py
noteblock_generator/core/session.py
noteblock_generator/core/world.py
noteblock_generator/data/file_utils.py
noteblock_generator/data/loader.py
noteblock_generator/data/schema.py
noteblock_generator/data/watcher.py
noteblock_generator-0.3.1.dist-info/METADATA
noteblock_generator-0.3.1.dist-info/WHEEL
noteblock_generator-0.3.1.dist-info/entry_points.txt
noteblock_generator-0.3.1.dist-info/RECORD
