Metadata-Version: 2.4
Name: noteblock-generator
Version: 0.3.1
Summary: Generate music in Minecraft noteblocks
Project-URL: Homepage, https://www.youtube.com/@felixfourcolor
Project-URL: Repository, https://github.com/FelixFourcolor/noteblock-generator
Author-email: Felix Fourcolor <felix.fourcolor@gmail.com>
License: MIT
Keywords: minecraft,noteblock
Requires-Python: <3.15,>=3.10
Requires-Dist: amulet-core>=1.9.32
Requires-Dist: msgspec>=0.20.0
Requires-Dist: typer>=0.20.0
Requires-Dist: watchfiles>=1.1.1
